clin/__init__.py
clin/clients/__init__.py
clin/clients/http_client.py
clin/clients/nakadi.py
clin/clients/nakadi_sql.py
clin/clinfile.py
clin/config.py
clin/models/__init__.py
clin/models/auth.py
clin/models/event_type.py
clin/models/shared.py
clin/models/sql_query.py
clin/models/subscription.py
clin/processor.py
clin/run.py
clin/utils.py
clin/yamlops.py
clin-1.8.0.dist-info/LICENSE
clin-1.8.0.dist-info/METADATA
clin-1.8.0.dist-info/WHEEL
clin-1.8.0.dist-info/entry_points.txt
clin-1.8.0.dist-info/RECORD
