Metadata-Version: 2.1
Name: clin
Version: 1.8.0
Summary: Cli for Nakadi resources management in Infrastructure as Code style
Home-page: https://github.com/zalando-incubator/clin
License: MIT
Keywords: Nakadi
Author: Dmitry Erokhin
Author-email: dmitry.erokhin@zalando.de
Requires-Python: >=3.7,<4.0
Classifier: Development Status :: 5 - Production/Stable
Classifier: Environment :: Console
Classifier: Intended Audience :: Developers
Classifier: License :: OSI Approved :: MIT License
Classifier: Natural Language :: English
Classifier: Programming Language :: Python :: 3
Classifier: Programming Language :: Python :: 3.7
Classifier: Programming Language :: Python :: 3.8
Classifier: Programming Language :: Python :: 3.9
Classifier: Programming Language :: Python :: 3.10
Classifier: Programming Language :: Python :: 3.11
Classifier: Topic :: Software Development :: Build Tools
Requires-Dist: click (>=8.1,<9.0)
Requires-Dist: colorama (>=0.4,<0.5)
Requires-Dist: deepdiff (>=6.7,<7.0)
Requires-Dist: pygments (>=2.17,<3.0)
Requires-Dist: pyyaml (>=6.0,<7.0)
Requires-Dist: requests (>=2.31,<3.0)
